bambora/__init__.py
bambora/base_objects.py
bambora/exceptions.py
bambora/misc.py
bambora/objects.py
bambora-0.1.0.dist-info/METADATA
bambora-0.1.0.dist-info/WHEEL
bambora-0.1.0.dist-info/top_level.txt
bambora-0.1.0.dist-info/RECORD
