Metadata-Version: 2.1
Name: bambora
Version: 0.1.0
Summary: Bambora Client API
Home-page: UNKNOWN
Author: Loïc Faure-Lacroix
Author-email: UNKNOWN
License: MIT
Platform: UNKNOWN
Classifier: Programming Language :: Python
Classifier: Programming Language :: Python :: 2.7
Requires-Dist: requests (==2.18.4)
